pdbpy/__init__.py
pdbpy/msf.py
pdbpy/parsing.py
pdbpy/pdb.py
pdbpy/primitivetypes.py
pdbpy/types.py
pdbpy/codeview/__init__.py
pdbpy/codeview/leafid.py
pdbpy/codeview/symbols.py
pdbpy/codeview/types.py
pdbpy/codeview/records/__init__.py
pdbpy/codeview/records/symbols/__init__.py
pdbpy/codeview/records/symbols/base.py
pdbpy/codeview/records/symbols/datasym.py
pdbpy/pe/records.py
pdbpy/streams/__init__.py
pdbpy/streams/pdbinfo.py
pdbpy/streams/typing.py
pdbpy/streams/debuginformationstream/__init__.py
pdbpy/streams/debuginformationstream/dbidbgheader.py
pdbpy/streams/debuginformationstream/dbistreamheader.py
pdbpy/streams/debuginformationstream/debuginformationstream.py
pdbpy/streams/debuginformationstream/moduleinformation.py
pdbpy/streams/debuginformationstream/sectionmap.py
pdbpy/streams/directorystream/__init__.py
pdbpy/streams/directorystream/streamdirectory.py
pdbpy/streams/globalsstream/globalsstream.py
pdbpy/streams/sectionheaderstream/__init__.py
pdbpy/streams/sectionheaderstream/sectionheaderstream.py
pdbpy/streams/symbolsstream/__init__.py
pdbpy/streams/symbolsstream/symbolsstream.py
pdbpy/streams/typestream/__init__.py
pdbpy/streams/typestream/parse.py
pdbpy/streams/typestream/pdbtypestream.py
pdbpy/streams/typestream/typestreamheader.py
pdbpy/streams/typestream/records/__init__.py
pdbpy/streams/typestream/records/array.py
pdbpy/streams/typestream/records/base.py
pdbpy/streams/typestream/records/baseclass.py
pdbpy/streams/typestream/records/bitfield.py
pdbpy/streams/typestream/records/codeviewrecordheader.py
pdbpy/streams/typestream/records/enum.py
pdbpy/streams/typestream/records/enumerate.py
pdbpy/streams/typestream/records/fieldlist.py
pdbpy/streams/typestream/records/member.py
pdbpy/streams/typestream/records/memberfunction.py
pdbpy/streams/typestream/records/method.py
pdbpy/streams/typestream/records/modifier.py
pdbpy/streams/typestream/records/nesttype.py
pdbpy/streams/typestream/records/onemethod.py
pdbpy-0.0.1.dist-info/LICENSE
pdbpy-0.0.1.dist-info/METADATA
pdbpy-0.0.1.dist-info/WHEEL
pdbpy-0.0.1.dist-info/top_level.txt
pdbpy-0.0.1.dist-info/RECORD
