Metadata-Version: 2.1
Name: pdbpy
Version: 0.0.1
Summary: Pure python implementation of parsing PDB debug information files
Author-email: Pierre LeMoine <pypi@luben.se>
License: MIT License
Project-URL: Homepage, https://github.com/DrInfiniteExplorer/pdbpy
Project-URL: Repository, https://github.com/DrInfiniteExplorer/pdbpy
Keywords: PDB,debug
Classifier: Development Status :: 3 - Alpha
Classifier: Programming Language :: Python :: 3
Classifier: License :: OSI Approved :: MIT License
Classifier: Operating System :: OS Independent
Requires-Python: >=3.12
License-File: LICENSE
